Workbook
Name Slicer_Category: #N/A
Name Slicer_Region: #N/A

Sheet Raw Data
A1: Order ID,Order Date,Region,Category,Sub-Category,Product Name,Sales,Quantity,Discount,Profit
A2: ORD-2025-10289,2025-12-02,West,Furniture ,Chairs,Ergonomic Mesh Chair,1298.71,10,0.15,-99.29
A3: ORD-2024-10010,01-21-2024,central,Office Supplies ,Storage,Desktop Organizer Box,172.45,4,0.15,9.58
A4: ORD-2024-10058,23/05/2024,CENTRAL,Technology,Accessories,Business Router Max,739.33,6,0.3,-9.55
A5: ,,,,,,,,,
A6: ORD-2024-10061,2024-05-30,WEST,Office Supplies,Paper,Gel Pens 12-Pack,$44.10,4,0.3,-7.14
A7: ORD-2024-10026,05/03/2024,EAST,Furniture,Tables,Executive Leather Chair,"$1,034.93",6,0.4,-418.13
A8: ORD-2024-10064,06-05-2024,West,OFFICE SUPPLIES,Storage,Heavy Duty Binder,153.5,7,0.2,-1.67
A9: ORD-2024-10093,2024-08-18,central,Technology,Accessories,Dual Screen Monitor,9796.31,10,0.05,2958.9
A10: ORD-2025-10185,06/04/2025,South,Office Supplies,Appliances,Heavy Duty Binder,115.42,3,0.05,21.25
A11: ORD-2025-10245,04/09/2025,East ,TECHNOLOGY,Accessories,Mechanical Keyboard,5316.3,9,0.05,1731.74
A12: ORD-2024-10047,05-01-2024,South ,Office Supplies ,Storage,Copy Paper 500 Sheets,544.27,6,0.15,18.4
... A315: ORD-2024-10103,09-03-2024,West ,Office Supplies ,Paper,Copy Paper 500 Sheets,366.12,8,0.1,45.77

Sheet Cleaned Data
A1: Order ID | B1: Order Date | C1: Region | D1: Category | E1: Sub-Category | F1: Product Name | G1: Sales | H1: Quantity | I1: Discount | J1: Profit | K1: Regional Manager | L1: Discount Range
A2: ORD-2025-10289 | B2: 45993 | C2: West | D2: Furniture | E2: Chairs | F2: Ergonomic Mesh Chair | G2: 1298.71 | H2: 10 | I2: 0.15 | J2: -99.29 | K2: =_xlfn.XLOOKUP(Order_ID_Order[[#This Row],[Region]],'Analysis Dashboard'!O$2:O$5,'Analysis Dashboard'!P$2:P$5) -> Rahul Verma | L2: =IF(I2<=0.1,"0-10%",IF(I2<=0.2,"11-20%",IF(I2<=0.3,"21-30%","31-40%"))) -> 11-20%
A3: ORD-2024-10010 | B3: 45312 | C3: Central | D3: Office Supplies | E3: Storage | F3: Desktop Organizer Box | G3: 172.45 | H3: 4 | I3: 0.15 | J3: 9.58 | K3: =_xlfn.XLOOKUP(Order_ID_Order[[#This Row],[Region]],'Analysis Dashboard'!O$2:O$5,'Analysis Dashboard'!P$2:P$5) -> Ankit Gupta | L3: =IF(I3<=0.1,"0-10%",IF(I3<=0.2,"11-20%",IF(I3<=0.3,"21-30%","31-40%"))) -> 11-20%
A4: ORD-2024-10058 | B4: 45435 | C4: Central | D4: Technology | E4: Accessories | F4: Business Router Max | G4: 739.33 | H4: 6 | I4: 0.3 | J4: -9.55 | K4: =_xlfn.XLOOKUP(Order_ID_Order[[#This Row],[Region]],'Analysis Dashboard'!O$2:O$5,'Analysis Dashboard'!P$2:P$5) -> Ankit Gupta | L4: =IF(I4<=0.1,"0-10%",IF(I4<=0.2,"11-20%",IF(I4<=0.3,"21-30%","31-40%"))) -> 21-30%
A5: ORD-2024-10061 | B5: 45442 | C5: West | D5: Office Supplies | E5: Paper | F5: Gel Pens 12-Pack | G5: 44.1 | H5: 4 | I5: 0.3 | J5: -7.14 | K5: =_xlfn.XLOOKUP(Order_ID_Order[[#This Row],[Region]],'Analysis Dashboard'!O$2:O$5,'Analysis Dashboard'!P$2:P$5) -> Rahul Verma | L5: =IF(I5<=0.1,"0-10%",IF(I5<=0.2,"11-20%",IF(I5<=0.3,"21-30%","31-40%"))) -> 21-30%
A6: ORD-2024-10026 | B6: 45415 | C6: East | D6: Furniture | E6: Tables | F6: Executive Leather Chair | G6: 1034.93 | H6: 6 | I6: 0.4 | J6: -418.13 | K6: =_xlfn.XLOOKUP(Order_ID_Order[[#This Row],[Region]],'Analysis Dashboard'!O$2:O$5,'Analysis Dashboard'!P$2:P$5) -> Priya Sharma | L6: =IF(I6<=0.1,"0-10%",IF(I6<=0.2,"11-20%",IF(I6<=0.3,"21-30%","31-40%"))) -> 31-40%
A7: ORD-2024-10064 | B7: 45448 | C7: West | D7: Office Supplies | E7: Storage | F7: Heavy Duty Binder | G7: 153.5 | H7: 7 | I7: 0.2 | J7: -1.67 | K7: =_xlfn.XLOOKUP(Order_ID_Order[[#This Row],[Region]],'Analysis Dashboard'!O$2:O$5,'Analysis Dashboard'!P$2:P$5) -> Rahul Verma | L7: =IF(I7<=0.1,"0-10%",IF(I7<=0.2,"11-20%",IF(I7<=0.3,"21-30%","31-40%"))) -> 11-20%
A8: ORD-2024-10093 | B8: 45522 | C8: Central | D8: Technology | E8: Accessories | F8: Dual Screen Monitor | G8: 9796.31 | H8: 10 | I8: 0.05 | J8: 2958.9 | K8: =_xlfn.XLOOKUP(Order_ID_Order[[#This Row],[Region]],'Analysis Dashboard'!O$2:O$5,'Analysis Dashboard'!P$2:P$5) -> Ankit Gupta | L8: =IF(I8<=0.1,"0-10%",IF(I8<=0.2,"11-20%",IF(I8<=0.3,"21-30%","31-40%"))) -> 0-10%
A9: ORD-2025-10185 | B9: 45812 | C9: South | D9: Office Supplies | E9: Appliances | F9: Heavy Duty Binder | G9: 115.42 | H9: 3 | I9: 0.05 | J9: 21.25 | K9: =_xlfn.XLOOKUP(Order_ID_Order[[#This Row],[Region]],'Analysis Dashboard'!O$2:O$5,'Analysis Dashboard'!P$2:P$5) -> Neha Singh | L9: =IF(I9<=0.1,"0-10%",IF(I9<=0.2,"11-20%",IF(I9<=0.3,"21-30%","31-40%"))) -> 0-10%
A10: ORD-2025-10245 | B10: 45756 | C10: East | D10: Technology | E10: Accessories | F10: Mechanical Keyboard | G10: 5316.3 | H10: 9 | I10: 0.05 | J10: 1731.74 | K10: =_xlfn.XLOOKUP(Order_ID_Order[[#This Row],[Region]],'Analysis Dashboard'!O$2:O$5,'Analysis Dashboard'!P$2:P$5) -> Priya Sharma | L10: =IF(I10<=0.1,"0-10%",IF(I10<=0.2,"11-20%",IF(I10<=0.3,"21-30%","31-40%"))) -> 0-10%
A11: ORD-2024-10047 | B11: 45413 | C11: South | D11: Office Supplies | E11: Storage | F11: Copy Paper 500 Sheets | G11: 544.27 | H11: 6 | I11: 0.15 | J11: 18.4 | K11: =_xlfn.XLOOKUP(Order_ID_Order[[#This Row],[Region]],'Analysis Dashboard'!O$2:O$5,'Analysis Dashboard'!P$2:P$5) -> Neha Singh | L11: =IF(I11<=0.1,"0-10%",IF(I11<=0.2,"11-20%",IF(I11<=0.3,"21-30%","31-40%"))) -> 11-20%
A12: ORD-2024-10076 | B12: 45483 | C12: West | D12: Technology | E12: Accessories | F12: Smartphone X1 | G12: 1902.77 | H12: 2 | I12: 0.3 | J12: -68.97 | K12: =_xlfn.XLOOKUP(Order_ID_Order[[#This Row],[Region]],'Analysis Dashboard'!O$2:O$5,'Analysis Dashboard'!P$2:P$5) -> Rahul Verma | L12: =IF(I12<=0.1,"0-10%",IF(I12<=0.2,"11-20%",IF(I12<=0.3,"21-30%","31-40%"))) -> 21-30%
A13: ORD-2025-10164 | B13: 45840 | C13: West | D13: Technology | E13: Machines | F13: Mechanical Keyboard | G13: 118.88 | H13: 1 | I13: 0.4 | J13: -17.44 | K13: =_xlfn.XLOOKUP(Order_ID_Order[[#This Row],[Region]],'Analysis Dashboard'!O$2:O$5,'Analysis Dashboard'!P$2:P$5) -> Rahul Verma | L13: =IF(I13<=0.1,"0-10%",IF(I13<=0.2,"11-20%",IF(I13<=0.3,"21-30%","31-40%"))) -> 31-40%
... A21: ORD-2024-10074 | B21: 45511 | C21: East | D21: Technology | E21: Accessories | F21: HD Web Camera | G21: 950.21 | H21: 2 | I21: 0.4 | J21: -155.29 | K21: =_xlfn.XLOOKUP(Order_ID_Order[[#This Row],[Region]],'Analysis Dashboard'!O$2:O$5,'Analysis Dashboard'!P$2:P$5) -> Priya Sharma | L21: =IF(I21<=0.1,"0-10%",IF(I21<=0.2,"11-20%",IF(I21<=0.3,"21-30%","31-40%"))) -> 31-40%
A22: ORD-2024-10105 | B22: 45544 | C22: East | D22: Technology | E22: Accessories | F22: Workstation PC Pro | G22: 5037.37 | H22: 6 | I22: 0.15 | J22: 970.77 | K22: =_xlfn.XLOOKUP(Order_ID_Order[[#This Row],[Region]],'Analysis Dashboard'!O$2:O$5,'Analysis Dashboard'!P$2:P$5) -> Priya Sharma | L22: =IF(I22<=0.1,"0-10%",IF(I22<=0.2,"11-20%",IF(I22<=0.3,"21-30%","31-40%"))) -> 11-20% | S22: {=_xlfn.XLOOKUP(1,{1,2,3},{"A","B","C"})} -> A
A23: ORD-2024-10138 | B23: 45637 | C23: West | D23: Office Supplies | E23: Paper | F23: Office Microwave | G23: 264.06 | H23: 5 | I23: 0.4 | J23: -72.55 | K23: =_xlfn.XLOOKUP(Order_ID_Order[[#This Row],[Region]],'Analysis Dashboard'!O$2:O$5,'Analysis Dashboard'!P$2:P$5) -> Rahul Verma | L23: =IF(I23<=0.1,"0-10%",IF(I23<=0.2,"11-20%",IF(I23<=0.3,"21-30%","31-40%"))) -> 31-40%
A24: ORD-2025-10207 | B24: 45796 | C24: East | D24: Office Supplies | E24: Paper | F24: Desktop Organizer Box | G24: 92.99 | H24: 1 | I24: 0 | J24: 22.4 | K24: =_xlfn.XLOOKUP(Order_ID_Order[[#This Row],[Region]],'Analysis Dashboard'!O$2:O$5,'Analysis Dashboard'!P$2:P$5) -> Priya Sharma | L24: =IF(I24<=0.1,"0-10%",IF(I24<=0.2,"11-20%",IF(I24<=0.3,"21-30%","31-40%"))) -> 0-10%
A25: ORD-2024-10077 | B25: 45489 | C25: West | D25: Office Supplies | E25: Appliances | F25: File Folders 100-Pack | G25: 77.64 | H25: 4 | I25: 0 | J25: 19.27 | K25: =_xlfn.XLOOKUP(Order_ID_Order[[#This Row],[Region]],'Analysis Dashboard'!O$2:O$5,'Analysis Dashboard'!P$2:P$5) -> Rahul Verma | L25: =IF(I25<=0.1,"0-10%",IF(I25<=0.2,"11-20%",IF(I25<=0.3,"21-30%","31-40%"))) -> 0-10%
A26: ORD-2025-10174 | B26: 45719 | C26: West | D26: Furniture | E26: Furnishings | F26: Ergonomic Mesh Chair | G26: 3619.51 | H26: 9 | I26: 0.2 | J26: -482.81 | K26: =_xlfn.XLOOKUP(Order_ID_Order[[#This Row],[Region]],'Analysis Dashboard'!O$2:O$5,'Analysis Dashboard'!P$2:P$5) -> Rahul Verma | L26: =IF(I26<=0.1,"0-10%",IF(I26<=0.2,"11-20%",IF(I26<=0.3,"21-30%","31-40%"))) -> 11-20%
A27: ORD-2024-10114 | B27: 45565 | C27: East | D27: Technology | E27: Accessories | F27: Mechanical Keyboard | G27: 991.59 | H27: 3 | I27: 0.15 | J27: 156.74 | K27: =_xlfn.XLOOKUP(Order_ID_Order[[#This Row],[Region]],'Analysis Dashboard'!O$2:O$5,'Analysis Dashboard'!P$2:P$5) -> Priya Sharma | L27: =IF(I27<=0.1,"0-10%",IF(I27<=0.2,"11-20%",IF(I27<=0.3,"21-30%","31-40%"))) -> 11-20%
A28: ORD-2024-10034 | B28: 45508 | C28: Central | D28: Furniture | E28: Furnishings | F28: Wooden Bookcase 5-Shelf | G28: 899.36 | H28: 4 | I28: 0 | J28: 105.88 | K28: =_xlfn.XLOOKUP(Order_ID_Order[[#This Row],[Region]],'Analysis Dashboard'!O$2:O$5,'Analysis Dashboard'!P$2:P$5) -> Ankit Gupta | L28: =IF(I28<=0.1,"0-10%",IF(I28<=0.2,"11-20%",IF(I28<=0.3,"21-30%","31-40%"))) -> 0-10%
A29: ORD-2025-10275 | B29: 45966 | C29: West | D29: Furniture | E29: Chairs | F29: Executive Leather Chair | G29: 4346.86 | H29: 8 | I29: 0.1 | J29: 21.1 | K29: =_xlfn.XLOOKUP(Order_ID_Order[[#This Row],[Region]],'Analysis Dashboard'!O$2:O$5,'Analysis Dashboard'!P$2:P$5) -> Rahul Verma | L29: =IF(I29<=0.1,"0-10%",IF(I29<=0.2,"11-20%",IF(I29<=0.3,"21-30%","31-40%"))) -> 0-10%
A30: ORD-2025-10252 | B30: 45919 | C30: Central | D30: Office Supplies | E30: Paper | F30: Whiteboard Markers 8-Pack | G30: 481.68 | H30: 10 | I30: 0.4 | J30: -148.11 | K30: =_xlfn.XLOOKUP(Order_ID_Order[[#This Row],[Region]],'Analysis Dashboard'!O$2:O$5,'Analysis Dashboard'!P$2:P$5) -> Ankit Gupta | L30: =IF(I30<=0.1,"0-10%",IF(I30<=0.2,"11-20%",IF(I30<=0.3,"21-30%","31-40%"))) -> 31-40%
A31: ORD-2024-10109 | B31: 45554 | C31: East | D31: Technology | E31: Accessories | F31: Mechanical Keyboard | G31: 3049.78 | H31: 6 | I31: 0.4 | J31: -481.44 | K31: =_xlfn.XLOOKUP(Order_ID_Order[[#This Row],[Region]],'Analysis Dashboard'!O$2:O$5,'Analysis Dashboard'!P$2:P$5) -> Priya Sharma | L31: =IF(I31<=0.1,"0-10%",IF(I31<=0.2,"11-20%",IF(I31<=0.3,"21-30%","31-40%"))) -> 31-40%
A32: ORD-2024-10004 | B32: 45296 | C32: West | D32: Office Supplies | E32: Appliances | F32: Office Microwave | G32: 117.61 | H32: 1 | I32: 0.05 | J32: 22.4 | K32: =_xlfn.XLOOKUP(Order_ID_Order[[#This Row],[Region]],'Analysis Dashboard'!O$2:O$5,'Analysis Dashboard'!P$2:P$5) -> Rahul Verma | L32: =IF(I32<=0.1,"0-10%",IF(I32<=0.2,"11-20%",IF(I32<=0.3,"21-30%","31-40%"))) -> 0-10%
A33: ORD-2024-10083 | B33: 45498 | C33: West | D33: Office Supplies | E33: Paper | F33: Copy Paper 500 Sheets | G33: 208.62 | H33: 6 | I33: 0.5 | J33: -88.95 | K33: =_xlfn.XLOOKUP(Order_ID_Order[[#This Row],[Region]],'Analysis Dashboard'!O$2:O$5,'Analysis Dashboard'!P$2:P$5) -> Rahul Verma | L33: =IF(I33<=0.1,"0-10%",IF(I33<=0.2,"11-20%",IF(I33<=0.3,"21-30%","31-40%"))) -> 31-40%
A34: ORD-2024-10094 | B34: 45522 | C34: West | D34: Office Supplies | E34: Pens & Art | F34: Copy Paper 500 Sheets | G34: 216.12 | H34: 4 | I34: 0.4 | J34: -60.95 | K34: =_xlfn.XLOOKUP(Order_ID_Order[[#This Row],[Region]],'Analysis Dashboard'!O$2:O$5,'Analysis Dashboard'!P$2:P$5) -> Rahul Verma | L34: =IF(I34<=0.1,"0-10%",IF(I34<=0.2,"11-20%",IF(I34<=0.3,"21-30%","31-40%"))) -> 31-40%
... A297: ORD-2024-10103 | B297: 45538 | C297: West | D297: Office Supplies | E297: Paper | F297: Copy Paper 500 Sheets | G297: 366.12 | H297: 8 | I297: 0.1 | J297: 45.77 | K297: =_xlfn.XLOOKUP(Order_ID_Order[[#This Row],[Region]],'Analysis Dashboard'!O$2:O$5,'Analysis Dashboard'!P$2:P$5) -> Rahul Verma | L297: =IF(I297<=0.1,"0-10%",IF(I297<=0.2,"11-20%",IF(I297<=0.3,"21-30%","31-40%"))) -> 0-10%

Sheet Analysis Dashboard
A1: SALES PERFORMANCE DASHBOARD | O1: Region | P1: Regional Manager
O2: East | P2: Priya Sharma
O3: West | P3: Rahul Verma
A4: Total Sales $498,985.55 | F4: Total Profit $60,215.38 | J4: Profit Margin 12.1% | O4: Central | P4: Ankit Gupta
O5: South | P5: Neha Singh
B20: Region | C20: Total sales | E20: Discount | F20: Average Profit
B21: Central | C21: 75575.2 | E21: 0-10% | F21: 602.97183
B22: East | C22: 101404.18 | E22: 11-20% | F22: 70.851791
B23: South | C23: 76103.06 | E23: 21-30% | F23: -136.56533
B24: West | C24: 245903.11 | E24: 31-40% | F24: -285.64765
B25: Grand Total | C25: 498985.55 | E25: Grand Total | F25: 203.43034
B27: Category | C27: Total sales | D27: Total Profit | E27: Profit Margin
B28: Furniture | C28: 119720.21 | D28: -8348.19 | E28: =D28/C28 -> -0.069730833
B29: Office Supplies | C29: 49795.84 | D29: 692.08 | E29: =D29/C29 -> 0.01389835
B30: Technology | C30: 329469.5 | D30: 67871.49 | E30: =D30/C30 -> 0.20600235
B31: Grand Total | C31: 498985.55 | D31: 60215.38 | E31: =D31/C31 -> 0.1206756
